py2srbcyr/__init__.py
py2srbcyr-1.1.1.dist-info/LICENSE
py2srbcyr-1.1.1.dist-info/METADATA
py2srbcyr-1.1.1.dist-info/WHEEL
py2srbcyr-1.1.1.dist-info/top_level.txt
py2srbcyr-1.1.1.dist-info/RECORD
