Metadata-Version: 2.1
Name: py2srbcyr
Version: 1.1.1
Summary: Transliteration of text in Latin into Serbian Cyrillic alphabet
Author-email: "Strana (eng: Page)" <zcprog+pypi@pm.me>
License: LGPL-3.0-or-later
Project-URL: homepage, https://github.com/strn/py2srbcyr
Project-URL: Bug Tracker, https://github.com/strn/py2srbcyr/issues
Classifier: Programming Language :: Python :: 3
Classifier: License :: OSI Approved :: GNU Lesser General Public License v3 or later (LGPLv3+)
Classifier: Operating System :: OS Independent
Requires-Python: >=3.4
License-File: LICENSE
